xia_module/__init__.py
xia_module/module.py
xia_module/cicd/__init__.py
xia_module/cicd/github.py
xia_module/templates/module/main.tf
xia_module/templates/module/variables.tf
xia_module-0.0.27.dist-info/LICENSE
xia_module-0.0.27.dist-info/METADATA
xia_module-0.0.27.dist-info/WHEEL
xia_module-0.0.27.dist-info/top_level.txt
xia_module-0.0.27.dist-info/RECORD
