Metadata-Version: 2.1
Name: xia-module
Version: 0.0.27
Requires-Python: >=3.9
License-File: LICENSE
Requires-Dist: ruamel.yaml
Requires-Dist: PyYAML
Requires-Dist: jinja2
